sized/__init__.py
sized/gen.py
sized-0.1.0.dist-info/LICENSE
sized-0.1.0.dist-info/WHEEL
sized-0.1.0.dist-info/METADATA
sized-0.1.0.dist-info/RECORD
