Metadata-Version: 2.1
Name: sized
Version: 0.1.0
Summary: Sized Generators with Decorators
Home-page: https://github.com/ionite34/sized
License: MIT
Keywords: generator,iterator,iter,sizedgenerator
Author: ionite34
Author-email: dev@ionite.io
Requires-Python: >=3.9,<3.12
Classifier: License :: OSI Approved :: MIT License
Classifier: Programming Language :: Python :: 3
Classifier: Programming Language :: Python :: 3.10
Classifier: Programming Language :: Python :: 3.9
Project-URL: Repository, https://github.com/ionite34/sized
